{"cameraMode":{"drawMode":0,"name":"Shaded","section":"Shading Mode"},"sceneLighting":false,"audioPlay":false,"sceneViewState":{"m_AlwaysRefresh":false,"showFog":true,"showSkybox":false,"showFlares":true,"showImageEffects":true,"showParticleSystems":true,"showVisualEffectGraphs":true,"m_FxEnabled":true},"in2DMode":false,"pivot":{"x":-2.1967837810516359,"y":2.355541229248047,"z":2.363243341445923},"rotation":{"x":0.03239114582538605,"y":-0.41924184560775759,"z":-0.01496833935379982,"w":-0.9071768522262573},"size":5.551714897155762,"orthographic":false}